setup.py
Flask_LoginManager.egg-info/PKG-INFO
Flask_LoginManager.egg-info/SOURCES.txt
Flask_LoginManager.egg-info/dependency_links.txt
Flask_LoginManager.egg-info/requires.txt
Flask_LoginManager.egg-info/top_level.txt
flask_loginmanager/__init__.py
flask_loginmanager/user_mixin.py