Metadata-Version: 1.0
Name: Flask-LoginManager
Version: 1.0.6
Summary: Flask Login Manager that supports multi-role and permissions, inspired by Flask-Login
Home-page: UNKNOWN
Author: rain
Author-email: rain@joymud.com
License: MIT
Keywords: flask,login,multi-role,permission
Platform: flask
